{
  "name": "AdjustToken",
  "fields": [
    {
      "fieldName": "name",
      "fieldType": "String"
    },
    {
      "fieldName": "description",
      "fieldType": "byte[]",
      "fieldTypeBlobContent": "text"
    },
    {
      "fieldName": "token",
      "fieldType": "Double"
    },
    {
      "fieldName": "price",
      "fieldType": "Double"
    },
    {
      "fieldName": "image",
      "fieldType": "byte[]",
      "fieldTypeBlobContent": "image"
    }
  ],
  "relationships": [],
  "changelogDate": "20201014073646",
  "entityTableName": "adjust_token",
  "dto": "mapstruct",
  "pagination": "no",
  "service": "serviceClass",
  "jpaMetamodelFiltering": false,
  "fluentMethods": true,
  "readOnly": false,
  "embedded": false,
  "clientRootFolder": "",
  "applications": "*"
}
